polygon_classes/__init__.py
polygon_classes/classes.py
polygon_classes-0.3.5.dist-info/WHEEL
polygon_classes-0.3.5.dist-info/METADATA
polygon_classes-0.3.5.dist-info/RECORD
