Metadata-Version: 2.1
Name: polygon-classes
Version: 0.3.5
Summary: Pydantic schemas for parsing and working with Polygon.io jsons
Requires-Python: >=3.8,<4.0
Classifier: Programming Language :: Python :: 3
Classifier: Programming Language :: Python :: 3.8
Classifier: Programming Language :: Python :: 3.9
Requires-Dist: pendulum (>=2.1.2,<3.0.0)
Requires-Dist: pydantic (>=1.6.1,<2.0.0)
